odoo8_addon_l10n_ca_account_check_writing-8.0.1.0.0.99.dev6-py2.7-nspkg.pth
odoo8_addon_l10n_ca_account_check_writing-8.0.1.0.0.99.dev6.dist-info/DESCRIPTION.rst
odoo8_addon_l10n_ca_account_check_writing-8.0.1.0.0.99.dev6.dist-info/METADATA
odoo8_addon_l10n_ca_account_check_writing-8.0.1.0.0.99.dev6.dist-info/RECORD
odoo8_addon_l10n_ca_account_check_writing-8.0.1.0.0.99.dev6.dist-info/WHEEL
odoo8_addon_l10n_ca_account_check_writing-8.0.1.0.0.99.dev6.dist-info/metadata.json
odoo8_addon_l10n_ca_account_check_writing-8.0.1.0.0.99.dev6.dist-info/namespace_packages.txt
odoo8_addon_l10n_ca_account_check_writing-8.0.1.0.0.99.dev6.dist-info/top_level.txt
odoo_addons/l10n_ca_account_check_writing/__init__.py
odoo_addons/l10n_ca_account_check_writing/__openerp__.py
odoo_addons/l10n_ca_account_check_writing/account_voucher.py
odoo_addons/l10n_ca_account_check_writing/company.py
odoo_addons/l10n_ca_account_check_writing/l10n_ca_account_check_writing_report.xml
odoo_addons/l10n_ca_account_check_writing/i18n/fr.po
odoo_addons/l10n_ca_account_check_writing/i18n/fr_CA.po
odoo_addons/l10n_ca_account_check_writing/i18n/l10n_ca_account_check_writing.pot
odoo_addons/l10n_ca_account_check_writing/i18n/nb_NO.po
odoo_addons/l10n_ca_account_check_writing/i18n/sl.po
odoo_addons/l10n_ca_account_check_writing/report/README.txt
odoo_addons/l10n_ca_account_check_writing/report/__init__.py
odoo_addons/l10n_ca_account_check_writing/report/l10n_ca_check_print.py
odoo_addons/l10n_ca_account_check_writing/report/l10n_ca_check_print.sxw
odoo_addons/l10n_ca_account_check_writing/report/l10n_ca_check_print_middle.rml
odoo_addons/l10n_ca_account_check_writing/report/l10n_ca_check_print_top.rml
odoo_addons/l10n_ca_account_check_writing/report/l10n_ca_check_print_top.sxw
odoo_addons/l10n_ca_account_check_writing/static/description/icon.png
odoo_addons/l10n_ca_account_check_writing/test/amount_in_word.yml
