Metadata-Version: 2.0
Name: odoo8-addon-l10n-ca-account-check-writing
Version: 8.0.1.0.0.99.dev6
Summary: Canada - Check Writing
Home-page: http://www.savoirfairelinux.com
Author: Savoir-faire Linux,Odoo Community Association (OCA)
Author-email: support@odoo-community.org
License: AGPL-3
Platform: UNKNOWN
Classifier: Programming Language :: Python
Classifier: Framework :: Odoo
Classifier: License :: OSI Approved :: GNU Affero General Public License v3
Requires-Python: ~=2.7
Requires-Dist: num2words
Requires-Dist: odoo (<9.0a,>=8.0a)
Requires-Dist: odoo8-addon-account-voucher-supplier-invoice-number
Requires-Dist: odoo8-addon-l10n-ca-toponyms
Requires-Dist: odoo8-addon-res-currency-print-on-check
